[
    {
        "type": "header",
        "text": {
            "type": "plain_text",
            "text": "<HEADER>",
            "emoji": true
        }
    },
    {
        "type": "context",
        "elements": [
            {
                "type": "plain_text",
                "text": "<LOGGROUP>",
                "emoji": true
            }
        ]
    },
    {
        "type": "section",
        "text": {
            "type": "mrkdwn",
            "text": <MESSAGE>
        }
    },
    {
        "type": "section",
        "text": {
            "type": "mrkdwn",
            "text": "<<URL>|bekijk logs>"
        }
    }
]